runner1c/__init__.py
runner1c/command.py
runner1c/common.py
runner1c/core.py
runner1c/exit_code.py
runner1c/logger.py
runner1c/parser.py
runner1c/build/README.md
runner1c/build/tools/epf/ChangeSafeModeForExtension.epf
runner1c/build/tools/epf/CloseAfterUpdate.epf
runner1c/build/tools/epf/FileCompareMxl.epf
runner1c/build/tools/epf/Runner1C.epf
runner1c/commands/__init__.py
runner1c/commands/base_for_test.py
runner1c/commands/create_base.py
runner1c/commands/create_epf.py
runner1c/commands/diff_mxl.py
runner1c/commands/dump_config.py
runner1c/commands/dump_epf.py
runner1c/commands/dump_extensions.py
runner1c/commands/file.py
runner1c/commands/load_config.py
runner1c/commands/load_extension.py
runner1c/commands/platform_check.py
runner1c/commands/reg_server.py
runner1c/commands/start.py
runner1c/commands/start_agent.py
runner1c/commands/sync.py
runner1c/commands/version.py
runner1c/commands/webinst.py
runner1c/tests/__init__.py
runner1c/tests/conftest.py
runner1c/tests/test_diff_mxl.py
runner1c/tests/test_sync_without_base.py
runner1c/tests/test_version.py
runner1c/tests/test_with_base.py
runner1c/tools/create_base_for_test.py
runner1c/tools/epf/ChangeSafeModeForExtension.xml
runner1c/tools/epf/CloseAfterUpdate.xml
runner1c/tools/epf/FileCompareMxl.xml
runner1c/tools/epf/Runner1C.xml
runner1c/tools/epf/ChangeSafeModeForExtension/Forms/Form.xml
runner1c/tools/epf/ChangeSafeModeForExtension/Forms/Form/Ext/Form.xml
runner1c/tools/epf/ChangeSafeModeForExtension/Forms/Form/Ext/Form/Module.bsl
runner1c/tools/epf/CloseAfterUpdate/Ext/ObjectModule.bsl
runner1c/tools/epf/CloseAfterUpdate/Forms/Managed.xml
runner1c/tools/epf/CloseAfterUpdate/Forms/Ordinary.xml
runner1c/tools/epf/CloseAfterUpdate/Forms/Managed/Ext/Form.xml
runner1c/tools/epf/CloseAfterUpdate/Forms/Managed/Ext/Form/Module.bsl
runner1c/tools/epf/CloseAfterUpdate/Forms/Ordinary/Ext/Form.bin
runner1c/tools/epf/CloseAfterUpdate/Forms/Ordinary/Ext/Form/Module.bsl
runner1c/tools/epf/FileCompareMxl/Forms/Form.xml
runner1c-0.63.dist-info/LICENSE
runner1c-0.63.dist-info/METADATA
runner1c-0.63.dist-info/WHEEL
runner1c-0.63.dist-info/entry_points.txt
runner1c-0.63.dist-info/top_level.txt
runner1c-0.63.dist-info/RECORD
